cone.fileupload-1.0a1-py3.9-nspkg.pth
cone/fileupload/__init__.py
cone/fileupload/tests.py
cone/fileupload/browser/__init__.py
cone/fileupload/browser/actions.py
cone/fileupload/browser/fileupload.pt
cone/fileupload/browser/fileupload.py
cone/fileupload/browser/templates.py
cone/fileupload/browser/toolbar.pt
cone/fileupload/browser/static/fileupload/cone.fileupload.css
cone/fileupload/browser/static/fileupload/cone.fileupload.js
cone/fileupload/browser/static/fileupload/cone.fileupload.min.js
cone/fileupload/browser/static/jquery-fileupload/jquery.fileupload-process.js
cone/fileupload/browser/static/jquery-fileupload/jquery.fileupload-ui.js
cone/fileupload/browser/static/jquery-fileupload/jquery.fileupload-validate.js
cone/fileupload/browser/static/jquery-fileupload/jquery.fileupload.css
cone/fileupload/browser/static/jquery-fileupload/jquery.fileupload.js
cone/fileupload/browser/static/jquery-fileupload/jquery.iframe-transport.js
cone/fileupload/browser/static/jquery-fileupload/vendor/jquery.ui.widget.js
cone/fileupload/browser/static/jquery-fileupload/vendor/tmpl.min.js
cone/fileupload/locale/cone.fileupload.pot
cone/fileupload/locale/de/LC_MESSAGES/cone.fileupload.mo
cone/fileupload/locale/de/LC_MESSAGES/cone.fileupload.po
cone.fileupload-1.0a1.dist-info/LICENSE.rst
cone.fileupload-1.0a1.dist-info/METADATA
cone.fileupload-1.0a1.dist-info/WHEEL
cone.fileupload-1.0a1.dist-info/namespace_packages.txt
cone.fileupload-1.0a1.dist-info/top_level.txt
cone.fileupload-1.0a1.dist-info/RECORD
