Metadata-Version: 2.1
Name: cone.fileupload
Version: 1.0a1
Summary: jQuery File Upload integration for cone.app
Home-page: http://github.com/conestack/cone.fileuplaod
Author: Cone Contributors
Author-email: dev@conestack.org
License: Simplified BSD
Keywords: node pyramid cone web
Classifier: Environment :: Web Environment
Classifier: Programming Language :: Python
Classifier: Topic :: Internet :: WWW/HTTP :: Dynamic Content
License-File: LICENSE.rst
Requires-Dist: setuptools
Requires-Dist: cone.app (>=1.0.3)
Provides-Extra: test
Requires-Dist: zope.testrunner ; extra == 'test'
